{"cached_at":1773538065,"payload":{"success":true,"message":"success","status_code":200,"data":{"tmdb_id":857422,"tmdb_type":"movie","ophim_id":"6981ca29f07c400a86c42124","slug":"hai-nguoi-yeu-nhau","imdb_id":"tt8085330","image_sizes":{"backdrop":{"original":"https:\/\/image.tmdb.org\/t\/p\/original","w1280":"https:\/\/image.tmdb.org\/t\/p\/w1280","w300":"https:\/\/image.tmdb.org\/t\/p\/w300","w780":"https:\/\/image.tmdb.org\/t\/p\/w780"},"poster":{"original":"https:\/\/image.tmdb.org\/t\/p\/original","w154":"https:\/\/image.tmdb.org\/t\/p\/w154","w185":"https:\/\/image.tmdb.org\/t\/p\/w185","w342":"https:\/\/image.tmdb.org\/t\/p\/w342","w500":"https:\/\/image.tmdb.org\/t\/p\/w500","w780":"https:\/\/image.tmdb.org\/t\/p\/w780","w92":"https:\/\/image.tmdb.org\/t\/p\/w92"}},"images":[{"width":1280,"height":720,"aspect_ratio":1.778,"type":"backdrop","file_path":"\/kGolZTr8fayhBrzEo5Rufetfvva.jpg"},{"width":1280,"height":720,"aspect_ratio":1.778,"type":"backdrop","file_path":"\/8mvfQ6ZHem0aHzC0GaUrJ7yx6M0.jpg"},{"width":525,"height":750,"aspect_ratio":0.7,"type":"poster","file_path":"\/y5kZViWaufPZLoYzPUmZxQUvOHs.jpg","iso_639_1":"ja"}]}}}