{"cached_at":1773579073,"payload":{"status":"success","message":"","data":{"seoOnPage":{"og_type":"website","titleHead":"Phim 21 | 21 vietsub | Phim 21 hay | Tuyển tập 21 mới nhất 2025","descriptionHead":"Phim 21 hay tuyển tập, phim 21 mới nhất, tổng hợp phim 21, 21 full HD, 21 vietsub, xem 21 online","og_image":["movies\/21-thumb.jpg","movies\/21-gram-thumb.jpg","movies\/21-cay-cau-thumb.jpg","movies\/lat-nguoc-21-gam-thumb.jpg","movies\/21-ngay-truoc-le-cuoi-thumb.jpg","movies\/nha-bep-dia-nguc-phan-21-thumb.jpg","movies\/xi-dach-thumb.jpg","movies\/di-tan-an-toan-tu-the-ky-21-thumb.jpg","movies\/21-ngay-thumb.jpg","movies\/luat-phap-va-trat-tu-nan-nhan-dac-biet-phan-21-thumb.jpg","movies\/com-hoc-duong-thumb.jpg","movies\/nguoi-anh-hung-21-tuoi-thumb.jpg"],"og_url":"tim-kiem?keyword=21"},"breadCrumb":[{"name":"Tìm kiếm phim: 21 - Trang 1","isCurrent":true,"position":2}],"titlePage":"Tìm kiếm phim: 21","items":[{"name":"21","origin_name":"21","alternative_names":["Miss Nobody,21 Blackjack,Quebrando a Banca,决胜21点,Oko bere,21 Black Jack,21: Black Jack,Las Vegas 21,鬥智21點,21 - Las Vegas ostroma,ラスベガスをぶっつぶせ,21: Las Vegas,21: A Última Cartada,21: Sansa vietii lui,Vrhunska igra,Двадцать одно,21 - Razpad Las Vegasa,決勝21點,Двадцять одне,21 - The Movie,Untitled Blackjack Picture,21: Blackjack,Xì Dách"],"slug":"21","type":"single","thumb_url":"21-thumb.jpg","poster_url":"21-poster.jpg","sub_docquyen":false,"chieurap":false,"time":"2g 2ph","episode_current":"Full","quality":"HD","lang":"Vietsub","lang_key":["vs"],"year":2008,"category":[{"id":"620f3d2b91fa4af90ab697fe","name":"Chính kịch","slug":"chinh-kich"}],"country":[{"id":"620a231fe0fc277084dfd7ce","name":"Âu Mỹ","slug":"au-my"}],"tmdb":{"type":"movie","id":"80652","season":null,"vote_average":5.3,"vote_count":19},"imdb":{"vote_average":6.8,"vote_count":278742,"id":"tt0478087"},"last_episodes":[{"server_name":"Vietsub #1","is_ai":false,"name":"Full"}],"modified":{"time":"2025-01-03T15:38:43.000Z"},"_id":"6220d8f58481266c5b7f0983"},{"name":"21 Gram","origin_name":"21 Grams","alternative_names":["21 Gramos,21 Gramm,21 Grammes,21 gramů,21 Gramas,21 grammaa,21그램,21 그램,21 grammi - Il peso dell'anima,Twenty-One Grams,21 gramos,21 Грама,21 grammes,21 gram,21 grammi,21 Grammaa,21 grammaria,21 γραμμάρια,21 gramm,21 Geram,21グラム,21 gramas,21 gramów,21 de grame,21 грам,21 грaмм,Двадцать один грамм,21 gramov,靈魂的重量,Những Mảnh Đời Bất Hạnh"],"slug":"21-gram","type":"single","thumb_url":"21-gram-thumb.jpg","poster_url":"21-gram-poster.jpg","sub_docquyen":false,"chieurap":false,"time":"2g 4phút","episode_current":"Full","quality":"HD","lang":"Vietsub","lang_key":["vs"],"year":2003,"category":[{"id":"620f3d2b91fa4af90ab697fe","name":"Chính kịch","slug":"chinh-kich"}],"country":[{"id":"620a231fe0fc277084dfd7ce","name":"Âu Mỹ","slug":"au-my"}],"tmdb":{"type":"movie","id":"470","season":null,"vote_average":7.325,"vote_count":3316},"imdb":{"vote_average":7.6,"vote_count":252163,"id":"tt0315733"},"last_episodes":[{"server_name":"Vietsub #1","is_ai":false,"name":"Full"}],"modified":{"time":"2022-09-01T22:32:18.000Z"},"_id":"630fb6760048e70b82ac8d35"},{"name":"21 Cây Cầu","origin_name":"21 Bridges","alternative_names":["17 Bridges,21 브릿지-테러 셧다운,Nueva York sin salida,MANHATTAN LOCKDOWN,Manhattan sin salida,21 Bridges (2019),21 Bridges - Jagd durch Manhattan,21 Köprü,21 моста,Crime Sem Saída,Crime sem Saída,Poursuite sous pression,21座桥,21 Mostů,21 silda,Manhattan Lockdown,21 γέφυρες,21 most,21 híd,21 Gsharim,City of Crime,21ブリッジ,21 tiltas,21 tilts,21 mostów,21 Pontes,21 Most,21 мост,21 Mostov,暴走曼哈頓,21 міст,21 ko'prik"],"slug":"21-cay-cau","type":"single","thumb_url":"21-cay-cau-thumb.jpg","poster_url":"21-cay-cau-poster.jpg","sub_docquyen":false,"chieurap":false,"time":"0 phút","episode_current":"Full","quality":"HD","lang":"Vietsub","lang_key":["vs"],"year":2019,"category":[{"id":"620a21b2e0fc277084dfd0c5","name":"Hành Động","slug":"hanh-dong"},{"id":"620a2293e0fc277084dfd489","name":"Phiêu Lưu","slug":"phieu-luu"}],"country":[{"id":"620a231fe0fc277084dfd7ce","name":"Âu Mỹ","slug":"au-my"}],"tmdb":{"type":"movie","id":"535292","season":null,"vote_average":6.8,"vote_count":2098},"imdb":{"vote_average":6.7,"vote_count":78966,"id":"tt8688634"},"last_episodes":[{"server_name":"Vietsub #1","is_ai":false,"name":"Full"}],"modified":{"time":"2022-12-13T11:54:33.000Z"},"_id":"639805891c255c1c746e1a59"},{"name":"Lật Ngược 21 Gam","origin_name":"Reverse 21 Grams","alternative_names":["Fan Zhuan 21 Ke"],"slug":"lat-nguoc-21-gam","type":"series","thumb_url":"lat-nguoc-21-gam-thumb.jpg","poster_url":"lat-nguoc-21-gam-poster.jpg","sub_docquyen":false,"chieurap":false,"time":"15 phút\/tập","episode_current":"Hoàn tất (19\/19)","quality":"HD","lang":"Vietsub","lang_key":["vs"],"year":2025,"category":[{"id":"620f84d291fa4af90ab6b3f4","name":"Bí ẩn","slug":"bi-an"}],"country":[{"id":"62093063196e9f4ab6b448b8","name":"Trung Quốc","slug":"trung-quoc"}],"tmdb":{"type":"tv","id":"296494","season":1,"vote_average":0,"vote_count":0},"imdb":{"vote_average":0,"vote_count":0,"id":null},"last_episodes":[{"server_name":"Vietsub #1","is_ai":false,"name":"19"}],"modified":{"time":"2025-08-12T11:55:27.000Z"},"_id":"6898595c0e6dc506bdfd911d"},{"name":"21 Ngày Trước Lễ Cưới","origin_name":"21 Ngày Trước Lễ Cưới","alternative_names":[],"slug":"21-ngay-truoc-le-cuoi","type":"tvshows","thumb_url":"21-ngay-truoc-le-cuoi-thumb.jpg","poster_url":"21-ngay-truoc-le-cuoi-poster.jpg","sub_docquyen":false,"chieurap":false,"time":"90 Phút\/tập","episode_current":"Hoàn Tất (14\/14)","quality":"HD","lang":"Vietsub","lang_key":["vs"],"year":2020,"category":[{"id":"620a220de0fc277084dfd16d","name":"Tình Cảm","slug":"tinh-cam"},{"id":"620a221de0fc277084dfd1c1","name":"Hài Hước","slug":"hai-huoc"}],"country":[{"id":"62093063196e9f4ab6b448b8","name":"Trung Quốc","slug":"trung-quoc"}],"tmdb":{"type":null,"id":"","season":null,"vote_average":0,"vote_count":0},"imdb":{"id":"","vote_average":0,"vote_count":0},"last_episodes":[{"server_name":"Vietsub #1","is_ai":false,"name":"13"}],"modified":{"time":"2023-09-07T23:42:32.000Z"},"_id":"64f9fd7525c3f47570c2340b"},{"name":"Nhà bếp địa ngục (Phần 21)","origin_name":"Hell's Kitchen (Season 21)","alternative_names":["Hells Kitchen (US),Hell's Kitchen (US),Hell's Kitchen,Hell's Kitchen USA,Кухнята на Ада,Pekelná Kuchyně,Gordon Ramsays Höllenküche,Hell's Kitchen: Cocina en el infierno,Kauhukeittiö,La Cuisine de l'Enfer,地獄廚房,Paklena kuhinja,Gordon Ramsay - A pokol konyhája,ヘルズ・キッチン〜地獄の厨房,Piekielna Kuchnia Gordona Ramsaya,Паклена кухиња,Адская кухня,Hell's Kitchen: Battle of the Ages,Hell's Kitchen: Battle of the States,Hell's Kitchen: Head Chefs Only,Hell's Kitchen: Las Vegas,Hell's Kitchen: Rookies vs Veterans,Hell's Kitchen: The American Dream,Hell's Kitchen: Young Guns"],"slug":"nha-bep-dia-nguc-phan-21","type":"tvshows","thumb_url":"nha-bep-dia-nguc-phan-21-thumb.jpg","poster_url":"nha-bep-dia-nguc-phan-21-poster.jpg","sub_docquyen":false,"chieurap":false,"time":"43 phút\/tập","episode_current":"Hoàn Tất (16\/16)","quality":"HD","lang":"Vietsub","lang_key":["vs"],"year":2022,"category":[{"id":"620e0e64d9648f114cde7728","name":"Tài Liệu","slug":"tai-lieu"}],"country":[{"id":"620a2370e0fc277084dfd91e","name":"Anh","slug":"anh"}],"tmdb":{"type":"tv","id":"2370","season":1,"vote_average":6.803,"vote_count":315},"imdb":{"vote_average":7.2,"vote_count":24140,"id":"tt0437005"},"last_episodes":[{"server_name":"Vietsub #1","is_ai":false,"name":"16"}],"modified":{"time":"2025-04-24T15:29:21.000Z"},"_id":"63ae7cb16414a08fbe47b9d1"},{"name":"Xì Dách","origin_name":"21","alternative_names":["21 - The Movie,決勝21點,Dvidešimt vienas,21 - Blackjack,21 - Oko berie,21 Kortspelet,21: blackjack,Quebrando a Banca,玩转21点,攻陷拉斯维加斯,21 - Vinci a Las Vegas,21 Blackjack,决胜21点,Oko bere,21 Black Jack,21: Black Jack,Las Vegas 21,鬥智21點,21 - Las Vegas ostroma,ラスベガスをぶっつぶせ,21: Las Vegas,21: A Última Cartada,21: Sansa vietii lui,Vrhunska igra,Двадцать одно,21 - Razpad Las Vegasa,Двадцять одне,Untitled Blackjack Picture,21: Blackjack"],"slug":"xi-dach","type":"single","thumb_url":"xi-dach-thumb.jpg","poster_url":"xi-dach-poster.jpg","sub_docquyen":false,"chieurap":false,"time":"Đang cập nhật","episode_current":"Full","quality":"HD","lang":"Vietsub","lang_key":["vs"],"year":2008,"category":[{"id":"620a22ace0fc277084dfd531","name":"Kinh Dị","slug":"kinh-di"}],"country":[{"id":"620a231fe0fc277084dfd7ce","name":"Âu Mỹ","slug":"au-my"}],"tmdb":{"type":"movie","id":"8065","season":null,"vote_average":6.693,"vote_count":4932},"imdb":{"vote_average":6.8,"vote_count":278742,"id":"tt0478087"},"last_episodes":[{"server_name":"Vietsub #1","is_ai":false,"name":"Full"}],"modified":{"time":"2024-10-19T10:18:48.000Z"},"_id":"623478b33c735a9a446e3183"},{"name":"Di Tản An Toàn Từ Thế Kỷ 21","origin_name":"Escape from the 21st Century","alternative_names":["从21世纪安全撤离,Cong 21 shiji anquan cheli,Escapando del siglo XXI,Evacuate from the 21st Century,Põgenemine 21 sajandist,Escape from the 21st century,Эвакуация из XXI века,Safe Evacuation from the 21st Century"],"slug":"di-tan-an-toan-tu-the-ky-21","type":"single","thumb_url":"di-tan-an-toan-tu-the-ky-21-thumb.jpg","poster_url":"di-tan-an-toan-tu-the-ky-21-poster.jpg","sub_docquyen":true,"chieurap":false,"time":"98 Phút","episode_current":"Full","quality":"HD","lang":"Vietsub","lang_key":["vs"],"year":2024,"category":[{"id":"620a221de0fc277084dfd1c1","name":"Hài Hước","slug":"hai-huoc"},{"id":"620a2282e0fc277084dfd435","name":"Viễn Tưởng","slug":"vien-tuong"},{"id":"620a229be0fc277084dfd4dd","name":"Khoa Học","slug":"khoa-hoc"}],"country":[{"id":"62093063196e9f4ab6b448b8","name":"Trung Quốc","slug":"trung-quoc"}],"tmdb":{"type":"movie","id":"1242372","season":null,"vote_average":6.837,"vote_count":101},"imdb":{"vote_average":6.4,"vote_count":1377,"id":"tt7171442"},"last_episodes":[{"server_name":"Vietsub #1","is_ai":false,"name":"Full"}],"modified":{"time":"2024-09-09T15:24:51.000Z"},"_id":"66deb0cf59734cba570e152e"},{"name":"21 Ngày","origin_name":"The Limbo","alternative_names":["掩埋的真相,掩埋,二十一天,Er Shi Yi Tian"],"slug":"21-ngay","type":"series","thumb_url":"21-ngay-thumb.jpg","poster_url":"21-ngay-poster.jpg","sub_docquyen":false,"chieurap":false,"time":"35 phút\/tập","episode_current":"Hoàn Tất (12\/12)","quality":"HD","lang":"Vietsub","lang_key":["vs"],"year":2024,"category":[{"id":"620f3d2b91fa4af90ab697fe","name":"Chính kịch","slug":"chinh-kich"},{"id":"620f84d291fa4af90ab6b3f4","name":"Bí ẩn","slug":"bi-an"}],"country":[{"id":"62093063196e9f4ab6b448b8","name":"Trung Quốc","slug":"trung-quoc"}],"tmdb":{"type":"tv","id":"263078","season":1,"vote_average":7,"vote_count":2},"imdb":{"vote_average":0,"vote_count":15,"id":"tt29363611"},"last_episodes":[{"server_name":"Vietsub #1","is_ai":false,"name":"12"}],"modified":{"time":"2024-10-03T19:59:59.000Z"},"_id":"66f57e6bc63a6bf2135d89cf"},{"name":"Luật Pháp Và Trật Tự: Nạn Nhân Đặc Biệt (Phần 21)","origin_name":"Law & Order: Special Victims Unit (Season 21)","alternative_names":["La Ley y el Orden: UVE,Law & Order: Unidade de Vítimas Especiais (SVU),Law & Order: Investigação Especial,Lei & Ordem: UVE,Law and Order: New York,La  Loi & l'Ordre : Unité spéciale,La  Loi & l'Ordre : USV,New York : Unité spéciale,قانون و نظم: واحد قربانیان ویژه,LAW & ORDER： 性犯罪特捜班,성범죄수사대: SVU,로 앤 오더: 성범죄 전담반,로앤오더: 성범죄전담반,로앤오더: 성범죄 전담반,Law & Order: 성범죄전담반,Law & Order: 성범죄 전담반,Law & Order: SVU,Law & Order: Special Victims Unit,La ley y el orden: Unidad de Víctimas Especiales,Закон и ред: Специални разследвания,Lei & Ordem: Unidade de Vítimas Especiais,La loi & l'ordre - Crimes sexuels,Zákon a porádek: Útvar pro zvlástní obeti,Law & Order: New York,Special Victims Unit,Seaduse nimel: Seksuaalkuritegude uurimisüksus,Law & Order: UVE,Ley y orden: UVE,Ley y orden: Unidad de Víctimas Especiales,Kova laki: Erikoisyksikkö,New York - Unité spéciale,Nomos kai taxi - Eidiki omada,Νόμος και τάξη: Ειδική ομάδα,Zakon i red: Odjel za žrtve,Esküdt ellenségek - Meggyalázott áldozatok,Esküdt ellenségek: Különleges ügyosztály,Különleges ügyosztály,Law & Order: Unità Speciale,LAW & ORDER:性犯罪特捜班,Įstatymas ir tvarka: Specialiųjų tyrimų skyrius,Lov og orden: New York,Prawo i porządek: Sekcja specjalna,Lei & Ordem: Unidade Especial,Lege si ordine: Brigada speciala,Ред и закон: Одељење за специјалне жртве,Закон и порядок: Специальный корпус,Zakon in red: Enota za posebne primere,Zákon a poriadok: Špeciálna jednotka,法律與秩序：特殊受害者,法網遊龍：特案組,Закон і порядок: Спеціальний корпус,L&O: SVU,Law & Order's Sex Crimes,SVU,Sex Crimes,Luật Pháp Và Trật Tự: Nạn Nhân Đặc Biệt,Law & Order - Unità vittime speciali"],"slug":"luat-phap-va-trat-tu-nan-nhan-dac-biet-phan-21","type":"series","thumb_url":"luat-phap-va-trat-tu-nan-nhan-dac-biet-phan-21-thumb.jpg","poster_url":"luat-phap-va-trat-tu-nan-nhan-dac-biet-phan-21-poster.jpg","sub_docquyen":false,"chieurap":false,"time":"43 phút\/tập","episode_current":"Hoàn Tất (20\/20)","quality":"HD","lang":"Vietsub","lang_key":["vs"],"year":2019,"category":[{"id":"620a2249e0fc277084dfd2e5","name":"Hình Sự","slug":"hinh-su"},{"id":"620f3d2b91fa4af90ab697fe","name":"Chính kịch","slug":"chinh-kich"},{"id":"620f84d291fa4af90ab6b3f4","name":"Bí ẩn","slug":"bi-an"}],"country":[{"id":"620a231fe0fc277084dfd7ce","name":"Âu Mỹ","slug":"au-my"}],"tmdb":{"type":"tv","id":"2734","season":21,"vote_average":7.938,"vote_count":4112},"imdb":{"vote_average":8.1,"vote_count":141292,"id":"tt0203259"},"last_episodes":[{"server_name":"Vietsub #1","is_ai":false,"name":"20"}],"modified":{"time":"2024-07-18T14:47:11.000Z"},"_id":"6698c87f4f7b4d21279e7ed6"},{"name":"Cớm Học Đường","origin_name":"21 Jump Street","alternative_names":["Comando Especial 1,21 Jump Street - O adresă de pomină,21 Jump Street: O adresă de pomină,Jump street 21,Infiltrados en clase,柒警出更,Anjos da Lei,Comando especial,Maço və botan,Внедрени в час,Agentes secundários,龙虎少年队,Comando Especial,21 Jump Street - A kopasz osztag,Rehov Jump 21,21ジャンプストリート,Мачо и ботан,Мачо мен ботан,Nevykeliai po priedanga,Džampstrīta 21,Agentes Secundários,21 Jump Street - O adresa de pomina,На тајном задатку,21 Jump Street: Mladenic v modrem,Liseli Polisler,龍虎少年隊,Мачо і ботан,Macho va botan"],"slug":"com-hoc-duong","type":"single","thumb_url":"com-hoc-duong-thumb.jpg","poster_url":"com-hoc-duong-poster.jpg","sub_docquyen":false,"chieurap":false,"time":"Đang cập nhật","episode_current":"Full","quality":"HD","lang":"Vietsub","lang_key":["vs"],"year":2012,"category":[{"id":"620a21b2e0fc277084dfd0c5","name":"Hành Động","slug":"hanh-dong"},{"id":"620a221de0fc277084dfd1c1","name":"Hài Hước","slug":"hai-huoc"}],"country":[{"id":"620a231fe0fc277084dfd7ce","name":"Âu Mỹ","slug":"au-my"}],"tmdb":{"type":"movie","id":"64688","season":null,"vote_average":6.883,"vote_count":10806},"imdb":{"vote_average":7.2,"vote_count":633925,"id":"tt1232829"},"last_episodes":[{"server_name":"Vietsub #1","is_ai":false,"name":"Full"}],"modified":{"time":"2024-10-12T10:36:20.000Z"},"_id":"623c73ae80a88d9a484bf0ca"},{"name":"Người Anh Hùng 21 Tuổi","origin_name":"Ikkis","alternative_names":["Twenty One","Двадцать один"],"slug":"nguoi-anh-hung-21-tuoi","type":"single","thumb_url":"nguoi-anh-hung-21-tuoi-thumb.jpg","poster_url":"nguoi-anh-hung-21-tuoi-poster.jpg","sub_docquyen":false,"chieurap":false,"time":"148 Phút","episode_current":"Full","quality":"HD","lang":"Vietsub","lang_key":["vs"],"year":2026,"category":[{"id":"620a2253e0fc277084dfd339","name":"Chiến Tranh","slug":"chien-tranh"},{"id":"620f3d2b91fa4af90ab697fe","name":"Chính kịch","slug":"chinh-kich"}],"country":[{"id":"620a2355e0fc277084dfd8ca","name":"Ấn Độ","slug":"an-do"}],"tmdb":{"type":"movie","id":"1196946","season":null,"vote_average":6.1,"vote_count":8},"imdb":{"id":"tt15464188","vote_average":0,"vote_count":0},"last_episodes":[{"server_name":"Vietsub #1","is_ai":false,"name":"Full"}],"modified":{"time":"2026-03-12T08:26:41.000Z"},"_id":"69a5a0cdf937c3b5a1132aaf"}],"params":{"type_slug":"tim-kiem","keyword":"21","filterCategory":[""],"filterCountry":[""],"filterYear":"","filterType":"","sortField":"_id","sortType":"desc","pagination":{"totalItems":106,"totalItemsPerPage":12,"currentPage":1,"pageRanges":3}},"type_list":"","APP_DOMAIN_FRONTEND":"https:\/\/ophim17.cc","APP_DOMAIN_CDN_IMAGE":"https:\/\/img.ophim.live"}}}