{"cached_at":1773847410,"payload":{"success":true,"message":"success","status_code":200,"data":{"tmdb_id":229858,"tmdb_type":"tv","tmdb_season":1,"ophim_id":"695a1e73da6ce23e8e94a7d4","slug":"fatestrange-fake","imdb_id":"tt32864316","image_sizes":{"backdrop":{"original":"https:\/\/image.tmdb.org\/t\/p\/original","w1280":"https:\/\/image.tmdb.org\/t\/p\/w1280","w300":"https:\/\/image.tmdb.org\/t\/p\/w300","w780":"https:\/\/image.tmdb.org\/t\/p\/w780"},"poster":{"original":"https:\/\/image.tmdb.org\/t\/p\/original","w154":"https:\/\/image.tmdb.org\/t\/p\/w154","w185":"https:\/\/image.tmdb.org\/t\/p\/w185","w342":"https:\/\/image.tmdb.org\/t\/p\/w342","w500":"https:\/\/image.tmdb.org\/t\/p\/w500","w780":"https:\/\/image.tmdb.org\/t\/p\/w780","w92":"https:\/\/image.tmdb.org\/t\/p\/w92"}},"images":[{"width":2560,"height":1440,"aspect_ratio":1.778,"type":"backdrop","file_path":"\/kJVYs2p9SlU6YRZ7pJ0fE5mog2S.jpg"},{"width":2205,"height":1240,"aspect_ratio":1.778,"type":"backdrop","file_path":"\/nvMDpmZJrXsDejZi0eGO9261gqL.jpg","iso_639_1":"ja"},{"width":2560,"height":1440,"aspect_ratio":1.778,"type":"backdrop","file_path":"\/oAEF8FVsx7FMQRdUv5Xu0Y3ZZqv.jpg"},{"width":1036,"height":1392,"aspect_ratio":0.744,"type":"poster","file_path":"\/aWHDOaCCSCo45Z9U3W081SvCnOX.jpg"},{"width":1465,"height":2048,"aspect_ratio":0.715,"type":"poster","file_path":"\/3hyh1skmlFKkuV2zNEDl0geH1hg.jpg"},{"width":770,"height":1080,"aspect_ratio":0.713,"type":"poster","file_path":"\/p2m5waZw1bLTRTKuxLxaH5dlogN.jpg"},{"width":770,"height":1080,"aspect_ratio":0.713,"type":"poster","file_path":"\/puwJjk8iUnsN6iWlnmybdReCrA8.jpg"},{"width":770,"height":1080,"aspect_ratio":0.713,"type":"poster","file_path":"\/l0eUWWaYQvx6aivJfbJ55UrA9g2.jpg"},{"width":770,"height":1080,"aspect_ratio":0.713,"type":"poster","file_path":"\/eiLkoKrFcxYGQDM3PZBwlz86GbH.jpg"},{"width":770,"height":1080,"aspect_ratio":0.713,"type":"poster","file_path":"\/aEzay6pCGp1K7UvUoDQe9pTdQxV.jpg"},{"width":770,"height":1080,"aspect_ratio":0.713,"type":"poster","file_path":"\/v5gXx7kCq8HRuFHZSl1Ixruh7Q0.jpg"},{"width":770,"height":1080,"aspect_ratio":0.713,"type":"poster","file_path":"\/ulmDn66M8um0xERZpuQWowwe8RU.jpg"},{"width":876,"height":1280,"aspect_ratio":0.684,"type":"poster","file_path":"\/7WaVsE2qpXt2SHRJLVDqZtRPWi3.jpg","iso_639_1":"uk"},{"width":2000,"height":3000,"aspect_ratio":0.667,"type":"poster","file_path":"\/2r5MEaLYl5lZxzgfSmrDybipngl.jpg","iso_639_1":"ja"},{"width":2000,"height":3000,"aspect_ratio":0.667,"type":"poster","file_path":"\/sdlzmriaPvraqXcO5EcnCmcvDhk.jpg","iso_639_1":"ja"},{"width":1560,"height":2340,"aspect_ratio":0.667,"type":"poster","file_path":"\/eyvPwzZSeepDxRBxobArtQACgqr.jpg","iso_639_1":"ru"},{"width":800,"height":1200,"aspect_ratio":0.667,"type":"poster","file_path":"\/lBsBJIGYV7c1Yizva8LpZhghY4j.jpg","iso_639_1":"ja"},{"width":1297,"height":1946,"aspect_ratio":0.666,"type":"poster","file_path":"\/vyJkPK8YZhQUpT0ivYwBWCUpXhX.jpg","iso_639_1":"ja"}]}}}